{
	"format_version": "1.12.0",
	"minecraft:geometry": [
		{
			"description": {
				"identifier": "geometry.unknown",
				"texture_width": 128,
				"texture_height": 128,
				"visible_bounds_width": 6,
				"visible_bounds_height": 3.5,
				"visible_bounds_offset": [0, 1.25, 0]
			},
			"bones": [
				{
					"name": "body",
					"pivot": [-0.25, 15.7375, -12.25],
					"rotation": [0, 87.5, 0]
				},
				{
					"name": "belly",
					"parent": "body",
					"pivot": [-14.91371, 13.85, -13.04552],
					"cubes": [
						{"origin": [-21.91371, 9.85, -17.04552], "size": [7, 10, 10], "uv": [26, 30]}
					]
				},
				{
					"name": "chest",
					"parent": "body",
					"pivot": [-9.41371, 15.35, -12.04552],
					"cubes": [
						{"origin": [-14.91371, 9.85, -17.04552], "size": [11, 11, 10], "uv": [0, 0]}
					]
				},
				{
					"name": "torso",
					"parent": "body",
					"pivot": [-21.91371, 13.85, -13.04552],
					"cubes": [
						{"origin": [-29.91371, 9.85, -17.04552], "size": [8, 9, 10], "uv": [0, 21]}
					]
				},
				{
					"name": "head",
					"parent": "body",
					"pivot": [-5.16371, 17.6375, -12.92052],
					"cubes": [
						{"origin": [-3.91371, 10.85, -17.04552], "size": [8, 9, 9], "uv": [33, 12]}
					]
				},
				{
					"name": "left_horn",
					"parent": "head",
					"pivot": [4.18629, 18.7, -10.54552],
					"rotation": [0, 0, 62.5]
				},
				{
					"name": "bone",
					"parent": "left_horn",
					"pivot": [4.18629, 18.7, -10.54552],
					"cubes": [
						{"origin": [3.18629, 17.7, -11.54552], "size": [2, 3, 2], "uv": [64, 49]}
					]
				},
				{
					"name": "bone2",
					"parent": "left_horn",
					"pivot": [3.47822, 21.03419, -10.54552],
					"rotation": [0, 0, -45],
					"cubes": [
						{"origin": [2.47822, 19.53419, -11.54552], "size": [2, 3, 2], "uv": [61, 0]}
					]
				},
				{
					"name": "bone3",
					"parent": "left_horn",
					"pivot": [1.85669, 21.7092, -10.54552],
					"rotation": [0, 0, -100],
					"cubes": [
						{"origin": [0.69802, 20.33095, -11.54552], "size": [2, 3, 2], "uv": [60, 44]}
					]
				},
				{
					"name": "bone4",
					"parent": "left_horn",
					"pivot": [0.22906, 20.63994, -10.54552],
					"rotation": [0, 0, -147.5],
					"cubes": [
						{"origin": [-0.81546, 19.36191, -11.54552], "size": [2, 3, 2], "uv": [35, 60]}
					]
				},
				{
					"name": "bone5",
					"parent": "left_horn",
					"pivot": [-0.73896, 19.08789, -10.54552],
					"rotation": [0, 0, 30],
					"cubes": [
						{"origin": [-1.70635, 18.23737, -11.54552], "size": [2, 1, 2], "uv": [15, 54]}
					]
				},
				{
					"name": "right_horn",
					"parent": "head",
					"pivot": [4.18629, 18.7, -14.54552],
					"rotation": [0, 0, 62.5]
				},
				{
					"name": "bone6",
					"parent": "right_horn",
					"pivot": [4.18629, 18.7, -14.54552],
					"cubes": [
						{"origin": [3.18629, 17.7, -15.54552], "size": [2, 3, 2], "uv": [53, 0]}
					]
				},
				{
					"name": "bone7",
					"parent": "right_horn",
					"pivot": [3.47822, 21.03419, -14.54552],
					"rotation": [0, 0, -45],
					"cubes": [
						{"origin": [2.47822, 19.53419, -15.54552], "size": [2, 3, 2], "uv": [50, 35]}
					]
				},
				{
					"name": "bone8",
					"parent": "right_horn",
					"pivot": [1.85669, 21.7092, -14.54552],
					"rotation": [0, 0, -100],
					"cubes": [
						{"origin": [0.69802, 20.33095, -15.54552], "size": [2, 3, 2], "uv": [50, 30]}
					]
				},
				{
					"name": "bone9",
					"parent": "right_horn",
					"pivot": [0.22906, 20.63994, -14.54552],
					"rotation": [0, 0, -147.5],
					"cubes": [
						{"origin": [-0.81546, 19.36191, -15.54552], "size": [2, 3, 2], "uv": [38, 50]}
					]
				},
				{
					"name": "bone10",
					"parent": "right_horn",
					"pivot": [-0.73896, 19.08789, -14.54552],
					"rotation": [0, 0, 30],
					"cubes": [
						{"origin": [-1.70635, 18.23737, -15.54552], "size": [2, 1, 2], "uv": [26, 28]}
					]
				},
				{
					"name": "nose",
					"parent": "head",
					"pivot": [2.08629, 7.85, -13.04552],
					"cubes": [
						{"origin": [3.08629, 13.85, -16.04552], "size": [7, 3, 7], "uv": [17, 50]},
						{"origin": [8.18629, 14.15, -14.04552], "size": [3, 4, 3], "uv": [54, 62]}
					]
				},
				{
					"name": "mouth",
					"parent": "nose",
					"pivot": [4.58629, 12.425, -12.54552],
					"cubes": [
						{"origin": [3.08629, 10.925, -16.04552], "size": [7, 3, 7], "uv": [32, 0]}
					]
				},
				{
					"name": "left_tusk",
					"parent": "mouth",
					"pivot": [10.69802, 12.53095, -10.09552],
					"rotation": [0, 0, 60]
				},
				{
					"name": "tusk_bone",
					"parent": "left_tusk",
					"pivot": [10.69802, 12.53095, -10.09552],
					"cubes": [
						{"origin": [9.69802, 11.03095, -11.09552], "size": [2, 3, 2], "uv": [0, 26]}
					]
				},
				{
					"name": "tusk_bone1",
					"parent": "left_tusk",
					"pivot": [9.97488, 14.47844, -10.09552],
					"rotation": [0, 0, -42.5],
					"cubes": [
						{"origin": [8.97488, 12.97844, -11.09552], "size": [2, 3, 2], "uv": [0, 21]}
					]
				},
				{
					"name": "right_tusk",
					"parent": "mouth",
					"pivot": [10.69802, 12.53095, -14.99552],
					"rotation": [0, 0, 60]
				},
				{
					"name": "tusk_bone2",
					"parent": "right_tusk",
					"pivot": [10.69802, 12.53095, -14.99552],
					"cubes": [
						{"origin": [9.69802, 11.03095, -15.99552], "size": [2, 3, 2], "uv": [0, 5]}
					]
				},
				{
					"name": "tusk_bone3",
					"parent": "right_tusk",
					"pivot": [9.97488, 14.47844, -14.99552],
					"rotation": [0, 0, -42.5],
					"cubes": [
						{"origin": [8.97488, 12.97844, -15.99552], "size": [2, 3, 2], "uv": [0, 0]}
					]
				},
				{
					"name": "front_left_leg",
					"parent": "body",
					"pivot": [-7.68871, 17.35, -4.54552],
					"rotation": [0, 0, -2.5]
				},
				{
					"name": "front_leg_left",
					"parent": "front_left_leg",
					"pivot": [-6.989, 16.88701, -4.54552],
					"cubes": [
						{"origin": [-11.18871, 8.85, -7.04552], "size": [7, 9, 5], "uv": [0, 40]}
					]
				},
				{
					"name": "elbo",
					"parent": "front_left_leg",
					"pivot": [-7.85821, 8.83561, -4.57715],
					"rotation": [0, 0, 2.5],
					"cubes": [
						{"origin": [-10.2897, 0.19593, -7.07715], "size": [5, 9, 5], "uv": [60, 30]}
					]
				},
				{
					"name": "front_right_leg",
					"parent": "body",
					"pivot": [-8.23805, 16.89165, -18.332],
					"rotation": [0, 0, -2.5]
				},
				{
					"name": "front_leg_right",
					"parent": "front_right_leg",
					"pivot": [-6.59777, 17.03119, -4.58914],
					"cubes": [
						{"origin": [-11.45115, 9.02272, -22.07487], "size": [7, 9, 5], "uv": [0, 40]}
					]
				},
				{
					"name": "elbo4",
					"parent": "front_right_leg",
					"pivot": [-8.09638, 8.83916, -19.60649],
					"rotation": [0, 0, 2.5],
					"cubes": [
						{"origin": [-10.4219, 0.34297, -22.10649], "size": [5, 9, 5], "uv": [60, 30]}
					]
				},
				{
					"name": "back_right_leg",
					"parent": "body",
					"pivot": [-26.68966, 15.35, -19.58914],
					"rotation": [0, 0, 0],
					"cubes": [
						{"origin": [-30.40719, 9.26329, -22.08914], "size": [7, 7, 5], "uv": [45, 50]}
					]
				},
				{
					"name": "elbo3",
					"parent": "back_right_leg",
					"pivot": [-27.02371, 9.13016, -19.58914],
					"cubes": [
						{"origin": [-29.4351, -0.35151, -22.0179], "size": [5, 10, 5], "uv": [0, 55]}
					]
				},
				{
					"name": "back_left_leg",
					"parent": "body",
					"pivot": [-26.68871, 14.35, -3.54552],
					"rotation": [0, 0, 0],
					"cubes": [
						{"origin": [-30.59083, 9.66541, -7.04552], "size": [7, 7, 5], "uv": [58, 5]}
					]
				},
				{
					"name": "elbo2",
					"parent": "back_left_leg",
					"pivot": [-27.25097, 8.53132, -4.54552],
					"cubes": [
						{"origin": [-30.01203, 0.05032, -7.13202], "size": [5, 10, 5], "uv": [20, 60]}
					]
				},
				{
					"name": "tail",
					"parent": "body",
					"pivot": [-31.41371, 14.575, -12.04552],
					"cubes": [
						{"origin": [-32.91371, 12.575, -14.04552], "size": [3, 4, 4], "uv": [40, 62]}
					]
				}
			]
		}
	]
}